Metadata-Version: 2.4
Name: x_4357_make_contract_validators_x
Version: 0.20.17
Summary: JSON schema validation toolkit.
Author-email: "RRGM (Software Tech Lead, Primus Pilus Night Watch AI Corp.)" <foo@bar.com>
Requires-Python: >=3.8
Requires-Dist: jsonschema<5,>=4.21.1
